LICENSE.txt
MANIFEST.in
requirements.txt
requirements_test.txt
setup.py
pyipconnect/__init__.py
pyipconnect.egg-info/PKG-INFO
pyipconnect.egg-info/SOURCES.txt
pyipconnect.egg-info/dependency_links.txt
pyipconnect.egg-info/not-zip-safe
pyipconnect.egg-info/pbr.json
pyipconnect.egg-info/requires.txt
pyipconnect.egg-info/top_level.txt
pyipconnect/bin/ipconnect