Metadata-Version: 1.0
Name: pyipconnect
Version: 0.0.8
Summary: Utility to connect to Alliance Internet (India).
Home-page: http://github.com/eka/pyipconnect
Author: Esteban (Eka) Feldman
Author-email: esteban.feldman@gmail.com
License: MIT
Platform: UNKNOWN
